snipslocalmusic/Snipsspec
snipslocalmusic/__init__.py
snipslocalmusic/snipslocalmusic.py
snipslocalmusic-1.0.dist-info/DESCRIPTION.rst
snipslocalmusic-1.0.dist-info/METADATA
snipslocalmusic-1.0.dist-info/RECORD
snipslocalmusic-1.0.dist-info/WHEEL
snipslocalmusic-1.0.dist-info/metadata.json
snipslocalmusic-1.0.dist-info/top_level.txt
