Metadata-Version: 2.0
Name: snipslocalmusic
Version: 1.0
Summary: Local music player skill for Snips
Home-page: https://github.com/snipsco/snips-skill-localmusic
Author: Michael Fester
Author-email: michael.fester@gmail.com
License: MIT
Keywords: snips
Platform: UNKNOWN
Requires-Dist: pygame
